Workbook

Sheet Cover
A2: Financial Model
A3: Integrated P&L · Balance Sheet · Cash Flow
B6: Company Name | E6: Naviel
B7: Prepared By | E7: Mark Wema
B8: Date | E8: 46027
B9: Model Version | E9: v1.0
B10: Currency | E10: USD ($000s)
B11: Fiscal Year End | E11: December 31
B14: Colour Conventions
B15: Blue text | D15: Hardcoded inputs - numbers I type in (assumptions, drivers)
B16: Black text | D16: Calculated values - all formulas; never hardcode in these cells
B17: Green text | D17: Cross-sheet links - values pulled from another tab in this workbook
B18: Red text | D18: External links - data linked from another file entirely
B19: Yellow fill | D19: Flagged cells - assumptions requiring review or data entry
B20: Blue fill | D20: Section headers - group rows within each statement
B21: Navy fill | D21: Column headers - year labels, statement titles
B23: Model Navigation
B24: Cover | D24: This page - model info and colour guide
B25: Assumptions | D25: All input drivers - only blue cells are edited here
B26: P&L | D26: Income Statement - revenue down to net income
B27: Balance Sheet | D27: Assets, liabilities and equity - must balance
B28: Cash Flow | D28: Operating, investing, financing activities
B29: Checks | D29: Model integrity - balance check, error flags

Sheet Assumptions
B2: Assumptions & Input Drivers | I2: Only edit BLUE cells
B3: Driver | C3: Notes | D3: 2023 | E3: 2024 | F3: 2025 | G3: 2026 | H3: 2027
B4: Revenue Drivers
B5: Revenue ($000s) - Historical | C5: Actual reported revenue | D5: 45000 | E5: 52000
B6: Revenue Growth Rate - Forecast | C6: YoY % growth assumption | F6: 0.12 | G6: 0.1 | H6: 0.09
B7: Average Selling Price ($) | C7: Per unit pricing | D7: 250 | E7: 265 | F7: 275 | G7: 285 | H7: 295
B8: Units Sold (000s) | C8: Volume driver | D8: 180 | E8: 196 | F8: 218 | G8: 240 | H8: 262
B10: Cost & Margin Drivers
B11: Cost of Goods Sold % | C11: COGS as % of revenue | D11: 0.42 | E11: 0.41 | F11: 0.4 | G11: 0.39 | H11: 0.385
B12: Gross Margin % | C12: Calculated - 1 minus COGS % | D12: =1-D11 -> 0.58 | E12: =1-E11 -> 0.59 | F12: =1-F11 -> 0.6 | G12: =1-G11 -> 0.61 | H12: =1-H11 -> 0.615
B13: R&D % of Revenue | C13: Research & development spend | D13: 0.08 | E13: 0.08 | F13: 0.09 | G13: 0.09 | H13: 0.08
B14: S&M % of Revenue | C14: Sales & marketing spend | D14: 0.15 | E14: 0.14 | F14: 0.14 | G14: 0.13 | H14: 0.13
B15: G&A % of Revenue | C15: General & admin spend | D15: 0.07 | E15: 0.07 | F15: 0.07 | G15: 0.06 | H15: 0.06
B17: Balance Sheet Drivers
B18: Days Sales Outstanding (DSO) | C18: Receivables collection days | D18: 45 | E18: 44 | F18: 42 | G18: 40 | H18: 40
B19: Days Inventory Outstanding (DIO) | C19: Inventory holding days | D19: 30 | E19: 30 | F19: 28 | G19: 28 | H19: 25
B20: Days Payable Outstanding (DPO) | C20: Payables payment days | D20: 35 | E20: 36 | F20: 38 | G20: 40 | H20: 42
B22: Capital & Tax Assumptions
B23: Capex % of Revenue | C23: Capital expenditure assumption | D23: 0.04 | E23: 0.04 | F23: 0.05 | G23: 0.05 | H23: 0.04
B24: Depreciation Life (years) | C24: Straight-line useful life | D24: 5 | E24: 5 | F24: 5 | G24: 5 | H24: 5
B25: Tax Rate | C25: Effective corporate tax rate | D25: 0.21 | E25: 0.21 | F25: 0.21 | G25: 0.21 | H25: 0.21
B26: Interest Rate on Debt | C26: Annual rate on outstanding debt | D26: 0.055 | E26: 0.055 | F26: 0.06 | G26: 0.06 | H26: 0.058
B29: Historical (2023-2024) | D29: Forecast (2025-2027) * edit blue cells

Sheet P&L
B2: Income Statement ($000s)
B3: Line Item | C3: Notes | D3: 2023A | E3: 2024A | F3: 2025E | G3: 2026E | H3: 2027E
B4: Revenue
B5: Revenue | C5: From Assumptions tab | D5: =Assumptions!D5 -> 45000 | E5: =Assumptions!E5 -> 52000 | F5: =E6*(1+Assumptions!F6) -> 58240 | G5: =F6*(1+Assumptions!G6) -> 64064 | H5: =G6*(1+Assumptions!H6) -> 69829.76
B6: Total Revenue | D6: =SUM(D5:D5) -> 45000 | E6: =SUM(E5:E5) -> 52000 | F6: =SUM(F5:F5) -> 58240 | G6: =SUM(G5:G5) -> 64064 | H6: =SUM(H5:H5) -> 69829.76
B8: Cost of Goods Sold
B9: COGS | C9: Revenue × COGS % | D9: =D6*Assumptions!D11 -> 18900 | E9: =E6*Assumptions!E11 -> 21320 | F9: =F6*Assumptions!F11 -> 23296 | G9: =G6*Assumptions!G11 -> 24984.96 | H9: =H6*Assumptions!H11 -> 26884.458
B10: Gross Profit | D10: =D6-D9 -> 26100 | E10: =E6-E9 -> 30680 | F10: =F6-F9 -> 34944 | G10: =G6-G9 -> 39079.04 | H10: =H6-H9 -> 42945.302
B11: Gross Margin % | C11: Gross Profit ÷ Revenue | D11: =D10/D6 -> 0.58 | E11: =E10/E6 -> 0.59 | F11: =F10/F6 -> 0.6 | G11: =G10/G6 -> 0.61 | H11: =H10/H6 -> 0.615
B13: Operating Expenses
B14: Research & Development | C14: Revenue × R&D % | D14: =D6*Assumptions!D13 -> 3600 | E14: =E6*Assumptions!E13 -> 4160 | F14: =F6*Assumptions!F13 -> 5241.6 | G14: =G6*Assumptions!G13 -> 5765.76 | H14: =H6*Assumptions!H13 -> 5586.3808
B15: Sales & Marketing | C15: Revenue × S&M % | D15: =D6*Assumptions!D14 -> 6750 | E15: =E6*Assumptions!E14 -> 7280 | F15: =F6*Assumptions!F14 -> 8153.6 | G15: =G6*Assumptions!G14 -> 8328.32 | H15: =H6*Assumptions!H14 -> 9077.8688
B16: General & Administrative | C16: Revenue × G&A % | D16: =D6*Assumptions!D15 -> 3150 | E16: =E6*Assumptions!E15 -> 3640 | F16: =F6*Assumptions!F15 -> 4076.8 | G16: =G6*Assumptions!G15 -> 3843.84 | H16: =H6*Assumptions!H15 -> 4189.7856
B17: Total Operating Expenses | D17: =D14+D15+D16 -> 13500 | E17: =E14+E15+E16 -> 15080 | F17: =F14+F15+F16 -> 17472 | G17: =G14+G15+G16 -> 17937.92 | H17: =H14+H15+H16 -> 18854.035
B19: EBITDA | C19: Earnings before interest, tax, D&A | D19: =D10-D17 -> 12600 | E19: =E10-E17 -> 15600 | F19: =F10-F17 -> 17472 | G19: =G10-G17 -> 21141.12 | H19: =H10-H17 -> 24091.267
B20: EBITDA Margin % | C20: EBITDA ÷ Revenue | D20: =D19/D6 -> 0.28 | E20: =E19/E6 -> 0.3 | F20: =F19/F6 -> 0.3 | G20: =G19/G6 -> 0.33 | H20: =H19/H6 -> 0.345
B22: Below EBITDA
B23: Depreciation & Amortisation | C23: Capex ÷ useful life (simplified) | D23: -1800 | E23: -1800 | F23: =-(F6*Assumptions!F23/Assumptions!F24) -> -582.4 | G23: =-(G6*Assumptions!G23/Assumptions!G24) -> -640.64 | H23: =-(H6*Assumptions!H23/Assumptions!H24) -> -558.63808
B24: EBIT (Operating Profit) | D24: =D19+D23 -> 10800 | E24: =E19+E23 -> 13800 | F24: =F19+F23 -> 16889.6 | G24: =G19+G23 -> 20500.48 | H24: =H19+H23 -> 23532.629
B25: Interest Expense | C25: Debt × interest rate | D25: -990 | E25: -1045 | F25: =-(15000*Assumptions!F26) -> -900 | G25: =-(14500*Assumptions!G26) -> -870 | H25: =-(14000*Assumptions!H26) -> -812
B26: Pre-Tax Income | D26: =D24+D25 -> 9810 | E26: =E24+E25 -> 12755 | F26: =F24+F25 -> 15989.6 | G26: =G24+G25 -> 19630.48 | H26: =H24+H25 -> 22720.629
B27: Income Tax | C27: Pre-Tax Income × tax rate | D27: =D26*Assumptions!D25 -> 2060.1 | E27: =E26*Assumptions!E25 -> 2678.55 | F27: =F26*Assumptions!F25 -> 3357.816 | G27: =G26*Assumptions!G25 -> 4122.4008 | H27: =H26*Assumptions!H25 -> 4771.3321
B29: Net Income | D29: =D26-D27 -> 7749.9 | E29: =E26-E27 -> 10076.45 | F29: =F26-F27 -> 12631.784 | G29: =G26-G27 -> 15508.079 | H29: =H26-H27 -> 17949.297
B30: Net Margin % | C30: Net Income ÷ Revenue | D30: =D29/D6 -> 0.17222 | E30: =E29/E6 -> 0.19377788 | F30: =F29/F6 -> 0.2168919 | G30: =G29/G6 -> 0.24207167 | H30: =H29/H6 -> 0.25704366

Sheet Balance Sheet
B2: Balance Sheet ($000s)
B3: Line Item | C3: Notes | D3: 2023A | E3: 2024A | F3: 2025E | G3: 2026E | H3: 2027E
B4: Assets
B5: Current Assets
B6: Cash & Cash Equivalents | C6: From Cash Flow statement - plug | D6: 8500 | E6: ='Cash Flow'!E23 -> 9200 | F6: ='Cash Flow'!F23 -> 18533.184 | G6: ='Cash Flow'!G23 -> 30529.703 | H6: ='Cash Flow'!H23 -> 45188.448
B7: Accounts Receivable | C7: DSO × Revenue / 365 | D7: =ROUND('P&L'!D6*Assumptions!D18/365,0) -> 5548 | E7: =ROUND('P&L'!E6*Assumptions!E18/365,0) -> 6268 | F7: =ROUND('P&L'!F6*Assumptions!F18/365,0) -> 6702 | G7: =ROUND('P&L'!G6*Assumptions!G18/365,0) -> 7021 | H7: =ROUND('P&L'!H6*Assumptions!H18/365,0) -> 7653
B8: Inventory | C8: DIO × COGS / 365 | D8: =ROUND('P&L'!D9*Assumptions!D19/365,0) -> 1553 | E8: =ROUND('P&L'!E9*Assumptions!E19/365,0) -> 1752 | F8: =ROUND('P&L'!F9*Assumptions!F19/365,0) -> 1787 | G8: =ROUND('P&L'!G9*Assumptions!G19/365,0) -> 1917 | H8: =ROUND('P&L'!H9*Assumptions!H19/365,0) -> 1841
B9: Other Current Assets | C9: Placeholder - update with actuals | D9: =ROUND('P&L'!D6*0.02,0) -> 900 | E9: =ROUND('P&L'!E6*0.02,0) -> 1040 | F9: =ROUND('P&L'!F6*0.02,0) -> 1165 | G9: =ROUND('P&L'!G6*0.02,0) -> 1281 | H9: =ROUND('P&L'!H6*0.02,0) -> 1397
B10: Total Current Assets | D10: =SUM(D6:D9) -> 16501 | E10: =SUM(E6:E9) -> 18260 | F10: =SUM(F6:F9) -> 28187.184 | G10: =SUM(G6:G9) -> 40748.703 | H10: =SUM(H6:H9) -> 56079.448
B12: Non-Current Assets
B13: Property, Plant & Equipment (gross) | C13: Prior year + Capex | D13: 22000 | E13: =D13-'Cash Flow'!E13 -> 24080 | F13: =E13-'Cash Flow'!F13 -> 26992 | G13: =F13-'Cash Flow'!G13 -> 30195.2 | H13: =G13-'Cash Flow'!H13 -> 32988.39
B14: Accumulated Depreciation | C14: Cumulative D&A | D14: -8000 | E14: =D14+'P&L'!E23 -> -9800 | F14: =E14+'P&L'!F23 -> -10382.4 | G14: =F14+'P&L'!G23 -> -11023.04 | H14: =G14+'P&L'!H23 -> -11581.678
B15: Net PP&E | D15: =D13+D14 -> 14000 | E15: =E13+E14 -> 14280 | F15: =F13+F14 -> 16609.6 | G15: =G13+G14 -> 19172.16 | H15: =H13+H14 -> 21406.712
B16: Intangibles & Other LT Assets | C16: Held flat - update if material | D16: 3500 | E16: 3500 | F16: 3500 | G16: 3500 | H16: 3500
B17: Deferred Tax & Other Long-Term Assets (Plug) | C17: Auto-balancing item - replace with actual deferred tax assets | D17: 0 | E17: 0 | F17: =(F34+F42)-(F10+F15+F16) -> 597 | G17: =(G34+G42)-(G10+G15+G16) -> 894 | H17: =(H34+H42)-(H10+H15+H16) -> 1234
B18: Total Non-Current Assets | D18: =SUM(D15:D17) -> 17500 | E18: =SUM(E15:E17) -> 17780 | F18: =SUM(F15:F17) -> 20706.6 | G18: =SUM(G15:G17) -> 23566.16 | H18: =SUM(H15:H17) -> 26140.712
B20: TOTAL ASSETS | D20: =D10+D18 -> 34001 | E20: =E10+E18 -> 36040 | F20: =F10+F18 -> 48893.784 | G20: =G10+G18 -> 64314.863 | H20: =H10+H18 -> 82220.16
B22: Liabilities
B23: Current Liabilities
B24: Accounts Payable | C24: DPO × COGS / 365 | D24: =ROUND('P&L'!D9*Assumptions!D20/365,0) -> 1812 | E24: =ROUND('P&L'!E9*Assumptions!E20/365,0) -> 2103 | F24: =ROUND('P&L'!F9*Assumptions!F20/365,0) -> 2425 | G24: =ROUND('P&L'!G9*Assumptions!G20/365,0) -> 2738 | H24: =ROUND('P&L'!H9*Assumptions!H20/365,0) -> 3094
B25: Short-Term Debt | C25: Held flat - revolver placeholder | D25: 2000 | E25: 2000 | F25: 2000 | G25: 2000 | H25: 2000
B26: Other Current Liabilities | C26: Accruals, deferred revenue - update with actuals | D26: =ROUND('P&L'!D6*0.025,0) -> 1125 | E26: =ROUND('P&L'!E6*0.025,0) -> 1300 | F26: 1700 | G26: 1800 | H26: 1900
B27: Total Current Liabilities | D27: =SUM(D24:D26) -> 4937 | E27: =SUM(E24:E26) -> 5403 | F27: =SUM(F24:F26) -> 6125 | G27: =SUM(G24:G26) -> 6538 | H27: =SUM(H24:H26) -> 6994
B29: Non-Current Liabilities
B30: Long-Term Debt | C30: Scheduled repayment | D30: 16000 | E30: 15500 | F30: 15000 | G30: 14500 | H30: 14000
B31: Other Long-Term Liabilities | D31: 800 | E31: 800 | F31: 800 | G31: 800 | H31: 800
B32: Total Non-Current Liabilities | D32: =SUM(D30:D31) -> 16800 | E32: =SUM(E30:E31) -> 16300 | F32: =SUM(F30:F31) -> 15800 | G32: =SUM(G30:G31) -> 15300 | H32: =SUM(H30:H31) -> 14800
B34: TOTAL LIABILITIES | D34: =D27+D32 -> 21737 | E34: =E27+E32 -> 21703 | F34: =F27+F32 -> 21925 | G34: =G27+G32 -> 21838 | H34: =H27+H32 -> 21794
B36: Equity
B37: Share Capital & Additional Paid-in Capital | D37: 12000 | E37: 12000 | F37: 12000 | G37: 12000 | H37: 12000
B38: Retained Earnings - Opening | C38: Prior year retained earnings | D38: -7486 | E38: -7739.45 | F38: =E41 -> 2337 | G38: =F41 -> 14968.784 | H38: =G41 -> 30476.863
B39: Net Income (current year) | C39: From P&L - green = cross-sheet link | D39: ='P&L'!D29 -> 7749.9 | E39: ='P&L'!E29 -> 10076.45 | F39: ='P&L'!F29 -> 12631.784 | G39: ='P&L'!G29 -> 15508.079 | H39: ='P&L'!H29 -> 17949.297
B40: Dividends Paid | C40: Set to zero - update if applicable | D40: 0 | E40: 0 | F40: 0 | G40: 0 | H40: 0
B41: Retained Earnings - Closing | D41: =D38+D39-D40 -> 263.9 | E41: =E38+E39-E40 -> 2337 | F41: =F38+F39-F40 -> 14968.784 | G41: =G38+G39-G40 -> 30476.863 | H41: =H38+H39-H40 -> 48426.16
B42: TOTAL EQUITY | D42: =D37+D41 -> 12263.9 | E42: =E37+E41 -> 14337 | F42: =F37+F41 -> 26968.784 | G42: =G37+G41 -> 42476.863 | H42: =H37+H41 -> 60426.16
B44: TOTAL LIABILITIES & EQUITY | D44: =D34+D42 -> 34000.9 | E44: =E34+E42 -> 36040 | F44: =F34+F42 -> 48893.784 | G44: =G34+G42 -> 64314.863 | H44: =H34+H42 -> 82220.16

Sheet Cash Flow
B2: Cash Flow Statement ($000s)
B3: Line Item | C3: Notes | D3: 2023A | E3: 2024A | F3: 2025E | G3: 2026E | H3: 2027E
B4: Operating Activities
B5: Net Income | C5: From P&L | D5: ='P&L'!D29 -> 7749.9 | E5: ='P&L'!E29 -> 10076.45 | F5: ='P&L'!F29 -> 12631.784 | G5: ='P&L'!G29 -> 15508.079 | H5: ='P&L'!H29 -> 17949.297
B6: Add: Depreciation & Amortisation | C6: Non-cash - add back | D6: 1800 | E6: 2080 | F6: =-('P&L'!F23) -> 582.4 | G6: =-('P&L'!G23) -> 640.64 | H6: =-('P&L'!H23) -> 558.63808
B7: Change in Accounts Receivable | C7: Increase = cash outflow | D7: -325 | E7: -745 | F7: =-('Balance Sheet'!F7-'Balance Sheet'!E7) -> -434 | G7: =-('Balance Sheet'!G7-'Balance Sheet'!F7) -> -319 | H7: =-('Balance Sheet'!H7-'Balance Sheet'!G7) -> -632
B8: Change in Inventory | C8: Increase = cash outflow | D8: -200 | E8: -300 | F8: =-('Balance Sheet'!F8-'Balance Sheet'!E8) -> -35 | G8: =-('Balance Sheet'!G8-'Balance Sheet'!F8) -> -130 | H8: =-('Balance Sheet'!H8-'Balance Sheet'!G8) -> 76
B9: Change in Accounts Payable | C9: Increase = cash inflow | D9: 385 | E9: 385 | F9: ='Balance Sheet'!F23-'Balance Sheet'!E23 -> 0 | G9: ='Balance Sheet'!G23-'Balance Sheet'!F23 -> 0 | H9: ='Balance Sheet'!H23-'Balance Sheet'!G23 -> 0
B10: Cash from Operations (CFO) | D10: =SUM(D5:D9) -> 9409.9 | E10: =SUM(E5:E9) -> 11496.45 | F10: =SUM(F5:F9) -> 12745.184 | G10: =SUM(G5:G9) -> 15699.719 | H10: =SUM(H5:H9) -> 17951.935
B12: Investing Activities
B13: Capital Expenditures | C13: Capex = Revenue × Capex % | D13: -1800 | E13: -2080 | F13: =-('P&L'!F6*Assumptions!F23) -> -2912 | G13: =-('P&L'!G6*Assumptions!G23) -> -3203.2 | H13: =-('P&L'!H6*Assumptions!H23) -> -2793.1904
B14: Cash from Investing (CFI) | D14: =D13 -> -1800 | E14: =E13 -> -2080 | F14: =F13 -> -2912 | G14: =G13 -> -3203.2 | H14: =H13 -> -2793.1904
B16: Financing Activities
B17: Debt Repayment | C17: Scheduled principal repayment | D17: -500 | E17: -500 | F17: -500 | G17: -500 | H17: -500
B18: Dividends Paid | C18: Set to zero - update if applicable | D18: 0 | E18: 0 | F18: 0 | G18: 0 | H18: 0
B19: Cash from Financing (CFF) | D19: =D17+D18 -> -500 | E19: =E17+E18 -> -500 | F19: =F17+F18 -> -500 | G19: =G17+G18 -> -500 | H19: =H17+H18 -> -500
B21: Net Change in Cash | D21: =D10+D14+D19 -> 7109.9 | E21: =E10+E14+E19 -> 8916.45 | F21: =F10+F14+F19 -> 9333.184 | G21: =G10+G14+G19 -> 11996.519 | H21: =H10+H14+H19 -> 14658.745
B22: Opening Cash Balance | C22: Prior year closing cash | D22: 1390.1 | E22: 283.55 | F22: =E23 -> 9200 | G22: =F23 -> 18533.184 | H22: =G23 -> 30529.703
B23: Closing Cash Balance | D23: =D22+D21 -> 8500 | E23: =E22+E21 -> 9200 | F23: =F22+F21 -> 18533.184 | G23: =G22+G21 -> 30529.703 | H23: =H22+H21 -> 45188.448

Sheet Checks
B2: Model Integrity Checks
B3: Check | C3: Description | D3: 2023A | E3: 2024A | F3: 2025E | G3: 2026E | H3: 2027E
B4: Balance Sheet Checks
B5: Balance Sheet balances? | C5: Total Assets = Total Liabilities + Equity (rounded to $000) | D5: =ROUND('Balance Sheet'!D20-'Balance Sheet'!D44,0) -> 0 | E5: =ROUND('Balance Sheet'!E20-'Balance Sheet'!E44,0) -> 0 | F5: =ROUND('Balance Sheet'!F20-'Balance Sheet'!F44,0) -> 0 | G5: =ROUND('Balance Sheet'!G20-'Balance Sheet'!G44,0) -> 0 | H5: =ROUND('Balance Sheet'!H20-'Balance Sheet'!H44,0) -> 0
B6: Cash ties to Cash Flow? | C6: Closing cash on Cash Flow = Cash on Balance Sheet. | D6: ='Balance Sheet'!D6-'Cash Flow'!D23 -> 0 | E6: ='Balance Sheet'!E6-'Cash Flow'!E23 -> 0 | F6: ='Balance Sheet'!F6-'Cash Flow'!F23 -> 0 | G6: ='Balance Sheet'!G6-'Cash Flow'!G23 -> 0 | H6: ='Balance Sheet'!H6-'Cash Flow'!H23 -> 0
B7: Net Income ties to P&L? | C7: Net Income on Cash Flow = Net Income on P&L. | D7: ='Cash Flow'!D5-'P&L'!D29 -> 0 | E7: ='Cash Flow'!E5-'P&L'!E29 -> 0 | F7: ='Cash Flow'!F5-'P&L'!F29 -> 0 | G7: ='Cash Flow'!G5-'P&L'!G29 -> 0 | H7: ='Cash Flow'!H5-'P&L'!H29 -> 0
B8: Green cell = $0 (balanced ) Red cell = non-zero (investigate )
B9: Status (OK if zero, ERROR if non-zero) | D9: =IF(ABS(D5)+ABS(D6)+ABS(D7)=0,"OK","ERROR") -> OK | E9: =IF(ABS(E5)+ABS(E6)+ABS(E7)=0,"OK","ERROR") -> OK | F9: =IF(ABS(F5)+ABS(F6)+ABS(F7)=0,"OK","ERROR") -> OK | G9: =IF(ABS(G5)+ABS(G6)+ABS(G7)=0,"OK","ERROR") -> OK | H9: =IF(ABS(H5)+ABS(H6)+ABS(H7)=0,"OK","ERROR") -> OK
B11: How to use this sheet
B12: 1. All checks above should show OK (i.e. the difference = $0). If any show ERROR, the model has a linking or formula issue.
B13: 2. The Balance Sheet check is the most important. If Assets ≠ Liabilities + Equity, something is missing or incorrectly linked.
B14: 3. Fix errors in the order shown: P&L first, then Cash Flow, then Balance Sheet. Errors cascade top-down.
B15: 4. Green text throughout the model = cross-sheet formula. Click a green cell and press Ctrl+[ to trace where it pulls from.
B16: 5. Blue text = hardcoded input. These are the only cells you should ever manually type into - everything else is calculated.
